Metadata-Version: 2.1
Name: feedly-to-sqlite
Version: 0.1
Summary: Save data from feedly to a SQLite database
Home-page: https://github.com/bcongdon/feedly-to-sqlite
Author: Benjamin Congdon
Author-email: me@bcon.gdn
License: UNKNOWN
Project-URL: Source, https://github.com/bcongdon/feedly-to-sqlite
Project-URL: Issues, https://github.com/bcongdon/feedly-to-sqlite/issues
Keywords: feedly sqlite export dogsheep
Platform: UNKNOWN
Classifier: Development Status :: 5 - Production/Stable
Classifier: Environment :: Console
Classifier: Programming Language :: Python :: 3
Classifier: Programming Language :: Python :: 3.6
Classifier: Programming Language :: Python :: 3.7
Classifier: Topic :: Database
Provides-Extra: test
